{
  "posts": [
    {
      "path": "posts/post-template",
      "main": "posts/post-template/index.md",
      "id": "post-template-02",
      "title": "サンプル記事",
      "description": "このブログの記事テンプレートです。",
      "category": "Design",
      "tags": [
        "HTML",
        "CSS",
        "JavaScript"
      ],
      "status": "publish",
      "created_at": "2019-10-01",
      "updated_at": "2019-10-01",
      "body": {
        "md": "---\r\nid: post-template-02\r\ntitle: サンプル記事\r\ndescription: このブログの記事テンプレートです。\r\ncategory: Design\r\ntags:\r\n    - HTML\r\n    - CSS\r\n    - JavaScript\r\nstatus: publish\r\ncreated_at: \"2019-10-01\"\r\nupdated_at: \"2019-10-01\"\r\n---\r\n\r\n## はじめに\r\n\r\nこのブログの記事はMarkdown記法で作成されています。\r\n\r\n## テキスト\r\n\r\nテキスト　テキスト　テキスト　テキスト　テキスト　テキスト　テキスト　テキスト　テキスト　テキスト　テキスト　テキスト　テキスト　テキスト　テキスト　テキスト　テキスト　テキスト　テキスト　テキスト　テキスト　テキスト　テキスト　テキスト　テキスト　テキスト　テキスト　テキスト　テキスト　テキスト　テキスト　テキスト\r\n\r\nテキスト　[リンクテキスト](./)　テキスト　テキスト\r\n\r\nテキスト　**強調テキスト**　テキスト　テキスト\r\n\r\nテキスト　`コードテキスト`　テキスト　テキスト\r\n\r\n## 見出し\r\n\r\n## 見出しレベル2\r\n\r\n### 見出しレベル3\r\n\r\n#### 見出しレベル4\r\n\r\n##### 見出しレベル5\r\n\r\n###### 見出しレベル6\r\n\r\n## リスト\r\n\r\n- テキスト\r\n- テキスト\r\n  - テキスト\r\n  - テキスト\r\n- テキスト\r\n- テキスト\r\n\r\n1. テキスト\r\n1. テキスト\r\n1. テキスト\r\n1. テキスト\r\n\r\n## ブロック\r\n\r\n> 引用ブロック\r\n> 引用ブロック\r\n> 引用ブロック\r\n\r\n```js\r\nconst text = 'コードブロック'\r\nconsole.log(text)\r\n```\r\n",
        "html": "<h2>はじめに</h2>\n<p>このブログの記事はMarkdown記法で作成されています。</p>\n<h2>テキスト</h2>\n<p>テキスト　テキスト　テキスト　テキスト　テキスト　テキスト　テキスト　テキスト　テキスト　テキスト　テキスト　テキスト　テキスト　テキスト　テキスト　テキスト　テキスト　テキスト　テキスト　テキスト　テキスト　テキスト　テキスト　テキスト　テキスト　テキスト　テキスト　テキスト　テキスト　テキスト　テキスト　テキスト</p>\n<p>テキスト　<a href=\"./\">リンクテキスト</a>　テキスト　テキスト</p>\n<p>テキスト　<strong>強調テキスト</strong>　テキスト　テキスト</p>\n<p>テキスト　<code>コードテキスト</code>　テキスト　テキスト</p>\n<h2>見出し</h2>\n<h2>見出しレベル2</h2>\n<h3>見出しレベル3</h3>\n<h4>見出しレベル4</h4>\n<h5>見出しレベル5</h5>\n<h6>見出しレベル6</h6>\n<h2>リスト</h2>\n<ul>\n<li>テキスト</li>\n<li>テキスト\n<ul>\n<li>テキスト</li>\n<li>テキスト</li>\n</ul>\n</li>\n<li>テキスト</li>\n<li>テキスト</li>\n</ul>\n<ol>\n<li>テキスト</li>\n<li>テキスト</li>\n<li>テキスト</li>\n<li>テキスト</li>\n</ol>\n<h2>ブロック</h2>\n<blockquote>\n<p>引用ブロック\n引用ブロック\n引用ブロック</p>\n</blockquote>\n<pre><code class=\"language-js\">const text = 'コードブロック'\nconsole.log(text)\n</code></pre>\n",
        "text": "はじめに\nこのブログの記事はMarkdown記法で作成されています。\nテキスト\nテキスト　テキスト　テキスト　テキスト　テキスト　テキスト　テキスト　テキスト　テキスト　テキスト　テキスト　テキスト　テキスト　テキスト　テキスト　テキスト　テキスト　テキスト　テキスト　テキスト　テキスト　テキスト　テキスト　テキスト　テキスト　テキスト　テキスト　テキスト　テキスト　テキスト　テキスト　テキスト\nテキスト　リンクテキスト　テキスト　テキスト\nテキスト　強調テキスト　テキスト　テキスト\nテキスト　コードテキスト　テキスト　テキスト\n見出し\n見出しレベル2\n見出しレベル3\n見出しレベル4\n見出しレベル5\n見出しレベル6\nリスト\nテキスト\nテキスト\n  テキスト\n  テキスト\nテキスト\nテキスト\nテキスト\nテキスト\nテキスト\nテキスト\nブロック\n> 引用ブロック\n> 引用ブロック\n> 引用ブロック\n`js\nconst text = 'コードブロック'\nconsole.log(text)\n`"
      },
      "resource": []
    },
    {
      "path": "posts/post-template-02",
      "main": "posts/post-template-02/index.md",
      "id": "post-template",
      "title": "サンプル記事",
      "description": "このブログの記事テンプレートです。",
      "category": "Cording",
      "tags": [
        "HTML",
        "CSS",
        "JavaScript"
      ],
      "status": "publish",
      "created_at": "2019-10-01",
      "updated_at": "",
      "body": {
        "md": "---\r\nid: post-template\r\ntitle: サンプル記事\r\ndescription: このブログの記事テンプレートです。\r\ncategory: Cording\r\ntags:\r\n    - HTML\r\n    - CSS\r\n    - JavaScript\r\nstatus: publish\r\ncreated_at: \"2019-10-01\"\r\nupdated_at: \"\"\r\n---\r\n\r\n## はじめに\r\n\r\nこのブログの記事はMarkdown記法で作成されています。",
        "html": "<h2>はじめに</h2>\n<p>このブログの記事はMarkdown記法で作成されています。</p>\n",
        "text": "はじめに\nこのブログの記事はMarkdown記法で作成されています。"
      },
      "resource": []
    }
  ],
  "tags": [
    "HTML",
    "CSS",
    "JavaScript"
  ],
  "resources": []
}